tfluna/__init__.py
tfluna/tfluna.py
tfluna/util.py
tfluna_driver-0.1.0.dist-info/LICENSE
tfluna_driver-0.1.0.dist-info/METADATA
tfluna_driver-0.1.0.dist-info/WHEEL
tfluna_driver-0.1.0.dist-info/top_level.txt
tfluna_driver-0.1.0.dist-info/RECORD
