Metadata-Version: 2.1
Name: tfluna-driver
Version: 0.1.0
Summary: Code to read measurements from a Tf-Luna LiDAR sensor.
Home-page: https://github.com/clementnuss/tfluna-python
Author: Clément Nussbaumer
Author-email: clement@astutus.org
License: UNKNOWN
Project-URL: Bug Tracker, https://github.com/clementnuss/tfluna-python
Platform: UNKNOWN
Classifier: Programming Language :: Python :: 3
Classifier: License :: OSI Approved :: MIT License
Classifier: Operating System :: OS Independent
Requires-Python: >=3.6
